[
  [
    {
      "key": "firstname",
      "type": "text",
      "contentType": "firstname",
      "label": "Prénom du visiteur",
      "autocomplete": "given-name",
      "placeholder": "Jean"
    },
    {
      "key": "lastname",
      "type": "text",
      "contentType": "lastname",
      "label": "Nom  du visiteur",
      "autocomplete": "family-name",
      "placeholder": "Dupont"
    },
    {
      "key": "firstnameAgent",
      "type": "text",
      "contentType": "firstname",
      "label": "Prénom de l'agent",
      "autocomplete": "given-name",
      "placeholder": "Jean"
    },
    {
      "key": "lastnameAgent",
      "type": "text",
      "contentType": "lastname",
      "label": "Nom de l'agent",
      "autocomplete": "family-name",
      "placeholder": "Dupont"
    },
    {
      "key": "telAgent",
      "type": "number",
      "contentType": "tel",
      "label": "Téléphone de l'agent",
      "autocomplete": "tel",
      "inputmode": "numeric",
      "pattern": "[0-9]{10}",
      "maxlength": 10
    },
    {
      "key": "mandate",
      "type": "text",
      "contentType": "mandate",
      "label": "Numéro de mandat"
    },
    {
      "key": "card",
      "type": "text",
      "contentType": "card",
      "label": "Numéro de carte professionnelle"
    },
    {
      "key": "agency",
      "type": "text",
      "contentType": "agency",
      "label": "Agence immobilière"
    }
  ],
  [
    {
      "key": "address",
      "type": "text",
      "contentType": "address",
      "label": "Adresse du bien",
      "autocomplete": "address-line1",
      "placeholder": "999 avenue de France"
    },
    {
      "key": "city",
      "type": "text",
      "contentType": "city",
      "label": "Ville",
      "autocomplete": "address-level2",
      "placeholder": "Paris"
    },
    {
      "key": "zipcode",
      "type": "number",
      "contentType": "zipcode",
      "label": "Code Postal",
      "autocomplete": "postal-code",
      "placeholder": "75001",
      "inputmode": "numeric",
      "pattern": "[0-9]{5}",
      "min": 1000,
      "max": 99999,
      "minlength": 4,
      "maxlength": 5
    }
  ],
  [
    {
      "key": "creationDate",
      "type": "date",
      "contentType": "creationDate",
      "label": "Date de création",
      "isHidden": true
    },
    {
      "key": "creationHour",
      "type": "time",
      "contentType": "creationHour",
      "label": "Heure de création",
      "isHidden": true
    },
    {
      "key": "datesortie",
      "type": "date",
      "contentType": "datesortie",
      "label": "Date de la visite",
      "pattern": "^([0][1-9]|[1-2][0-9]|30|31)/([0][1-9]|10|11|12)/(19[0-9][0-9]|20[0-1][0-9]|2020)",
      "autocomplete": ""
    },
    {
      "key": "heuresortie",
      "type": "time",
      "contentType": "heuresortie",
      "label": "Heure de la visite",
      "autocomplete": ""
    }
  ]
]
